[{"h": "Кто она", "p": ["Драупади — дочь Друпады, супруга пятерых Пандавов, великая преданная Кришны.", "Кришна дорожил ею как Своей подругой и сестрой."], "see": [{"id": "arjuna", "t": "Арджуна"}, {"id": "krishna", "t": "Шри Кришна"}]}, {"h": "Спасение в собрании", "p": ["Когда Духшасана пытался обесчестить её, сорвав сари, она воздела руки и всецело предалась Кришне.", "Господь явил безграничную ткань, и честь её осталась нетронутой."], "see": [{"id": "krishna", "t": "Шри Кришна"}]}, {"h": "Образец предания", "p": ["Её зов к Кришне — образец полного предания (шаранагати).", "Тот, кто целиком уповает на Господа, никогда не будет посрамлён."], "see": [{"id": "krishna", "t": "Шри Кришна"}]}]