[{"h": "Кто он", "p": ["Говинда Гхош — старший из трёх братьев Гхош (Говинда, Мадхава, Васудева), прославленных певцов киртана.", "Он — спутник Нитьянанды Прабху."], "see": [{"id": "vasudeva-ghosh", "t": "Васудева Гхош"}, {"id": "nityananda", "t": "Нитьянанда Прабху"}]}, {"h": "Певец санкиртаны", "p": ["Его пение приводило Махапрабху в восторг любви.", "По преданию, Божество Господа Сам совершало его поминальный обряд (шраддху), ибо у него не было сына."], "see": [{"id": "chaitanya", "t": "Шри Кришна Чайтанья Махапрабху"}]}]