[{"h": "Кто он", "p": ["Лочана дас Тхакур — поэт-преданный, автор «Чайтанья-мангалы» и множества любимых бенгальских песен.", "Его песни поют в киртане по сей день."], "see": [{"id": "chaitanya", "t": "Шри Кришна Чайтанья Махапрабху"}, {"id": "narottama-dasa-thakura", "t": "Нароттама дас Тхакур"}]}, {"h": "«Чайтанья-мангала»", "p": ["В этом труде он воспел игры Махапрабху просто и сладостно.", "Его бхаджаны полны любви и разлуки с Господом."], "see": [{"id": "chaitanya", "t": "Шри Кришна Чайтанья Махапрабху"}]}]