[{"h": "Кто он", "p": ["Шрила Прабодхананда Сарасвати — великий ачарья и поэт-преданный, автор «Радха-раса-судханидхи», «Вриндавана-махимамриты» и «Чайтанья-чандрамриты».", "Он встретил Махапрабху во время Его паломничества по Югу Индии."], "see": [{"id": "chaitanya", "t": "Шри Кришна Чайтанья Махапрабху"}, {"id": "radharani", "t": "Шримати Радхарани"}]}, {"h": "Поэт сладостной расы", "p": ["Его стихи воспевают величие Вриндавана и сокровенную любовь Радхи.", "Они — сокровище для тех, кто стремится к высшей преданности."], "see": [{"id": "krishna", "t": "Шри Кришна"}]}]