[{"h": "Кто она", "p": ["Рукмини — главная царица Кришны в Двараке, воплощение богини Лакшми.", "Она — образец преданной супруги."], "see": [{"id": "krishna", "t": "Шри Кришна"}, {"id": "balarama", "t": "Баларама"}]}, {"h": "Похищение по любви", "p": ["Она написала Кришне письмо, моля забрать её.", "В день, когда её хотели выдать за Шишупалу, Кришна увёз её на колеснице."], "cite": [{"ref": "ШБ 10.52", "to": "/book/sb/10/52"}], "see": [{"id": "shishupala", "t": "Шишупала"}]}, {"h": "Мать Прадьюмны", "p": ["Её сын — Прадьюмна, воплощение Камадевы.", "Её преданность Господу непоколебима."], "see": [{"id": "pradyumna", "t": "Прадьюмна"}]}, {"h": "Настроение Лакшми", "p": ["Как Лакшми, она вечно служит Господу с любовью и почтением.", "В Двараке она являет величие супружеской преданности."], "see": [{"id": "krishna", "t": "Шри Кришна"}]}]