[{"h": "Кто он", "p": ["Сандипани Муни — духовный учитель Кришны и Баларамы в Авантипуре (Удджайн).", "Под его началом Господь прошёл обучение."], "see": [{"id": "krishna", "t": "Шри Кришна"}, {"id": "balarama", "t": "Баларама"}]}, {"h": "Ученик-Господь", "p": ["Кришна овладел всеми шестьюдесятью четырьмя искусствами за шестьдесят четыре дня.", "В дар учителю Он вернул из обители смерти его погибшего сына."], "cite": [{"ref": "ШБ 10.45", "to": "/book/sb/10/45"}], "see": [{"id": "krishna", "t": "Шри Кришна"}]}]