[{"h": "Кто она", "p": ["Шачидеви — мать Шри Чайтаньи Махапрабху, супруга Джаганнатхи Мишры.", "В играх Кришны она — Яшода, мать Господа."], "see": [{"id": "chaitanya", "t": "Шри Кришна Чайтанья Махапрабху"}, {"id": "jagannatha-mishra", "t": "Джаганнатха Мишра"}]}, {"h": "Мать Господа", "p": ["Её материнская любовь к Нимаю беспредельна.", "Она претерпела разлуку, когда Господь принял санньясу."], "cite": [{"ref": "ЧЧ, Ади 13", "to": "/book/cc/adi/13"}], "see": [{"id": "yashoda", "t": "Яшода"}]}, {"h": "Прощение оскорблений", "p": ["По просьбе Господа она простила Адвайту и других.", "Её сердце было исполнено любви и смирения."], "see": [{"id": "chaitanya", "t": "Шри Кришна Чайтанья Махапрабху"}]}]