[{"h": "Кто он", "p": ["Валлабхачарья — основатель Пушти-марги (Валлабха-сампрадаи), проповедник шуддха-адвайты и великий преданный Кришны (Шринатхджи).", "Он был современником Шри Чайтаньи."], "see": [{"id": "krishna", "t": "Шри Кришна"}, {"id": "chaitanya", "t": "Шри Кришна Чайтанья Махапрабху"}]}, {"h": "Путь милости", "p": ["Его учение «пушти» — путь чистой милости Господа, обретаемой через любовное служение.", "В беседах с Махапрабху и Госвами раскрывалась сладость преданности."], "see": [{"id": "krishna", "t": "Шри Кришна"}]}]