[{"h": "Кто он", "p": ["Виджая — второй страж врат Вайкунтхи (вместе с Джаей), проклятый Четырьмя Кумарами.", "Вражда, обращённая к Богу, тоже привела его обратно к Нему."], "see": [{"id": "vishnu", "t": "Вишну"}, {"id": "four-kumaras", "t": "Четыре Кумара"}]}, {"h": "Враги-преданные", "p": ["Он рождался как Хираньякша, Кумбхакарна и Дантавакра — и каждый раз был сражён Господом.", "Так, исполнив роль врага, он возвращался на Вайкунтху."], "cite": [{"ref": "ШБ 7.1", "to": "/book/sb/7/1"}], "see": [{"id": "jaya", "t": "Джая"}, {"id": "shishupala", "t": "Шишупала"}]}]